setsail_workflow_py/__init__.py
ss_pyworkflow-0.1.2.dist-info/licenses/LICENSE
ss_pyworkflow-0.1.2.dist-info/METADATA
ss_pyworkflow-0.1.2.dist-info/WHEEL
ss_pyworkflow-0.1.2.dist-info/top_level.txt
ss_pyworkflow-0.1.2.dist-info/RECORD
