Metadata-Version: 2.4
Name: ss-pyworkflow
Version: 0.1.2
Summary: This is for workflow tracing on python environment.
Author-email: Kenny Chow <kennychow@setsailsoftware.com>
License:                                  Apache License
Project-URL: Homepage, https://github.com/Kenny-Setsail/setsail_workflow_py
Requires-Python: >=3.8
License-File: LICENSE
Requires-Dist: aiohttp
Requires-Dist: loguru
Requires-Dist: pydantic
Dynamic: license-file
